mpu/__init__.py
mpu/_version.py
mpu/aws.py
mpu/datetime.py
mpu/decorators.py
mpu/geometry.py
mpu/image.py
mpu/io.py
mpu/math.py
mpu/ml.py
mpu/path.py
mpu/pd.py
mpu/shell.py
mpu/string.py
mpu/data/countries.csv
mpu/data/iban.csv
mpu/data/laguages.csv.gz
mpu/data/sources.txt
mpu/datastructures/__init__.py
mpu/datastructures/trie/__init__.py
mpu/datastructures/trie/base.py
mpu/datastructures/trie/char_trie.py
mpu/datastructures/trie/full_prefix_dict.py
mpu/datastructures/trie/string_trie.py
mpu/units/__init__.py
mpu/units/currencies.csv
mpu-0.23.1.dist-info/LICENSE
mpu-0.23.1.dist-info/METADATA
mpu-0.23.1.dist-info/WHEEL
mpu-0.23.1.dist-info/top_level.txt
mpu-0.23.1.dist-info/RECORD
