Metadata-Version: 2.1
Name: mpu
Version: 0.23.1
Summary: Martins Python Utilities
Home-page: https://github.com/MartinThoma/mpu
Author: Martin Thoma
Author-email: info@martin-thoma.de
Maintainer: Martin Thoma
Maintainer-email: info@martin-thoma.de
License: MIT
Download-URL: https://github.com/MartinThoma/mpu
Keywords: utility
Platform: Linux
Classifier: Development Status :: 3 - Alpha
Classifier: Environment :: Console
Classifier: Intended Audience :: Developers
Classifier: Intended Audience :: Information Technology
Classifier: License :: OSI Approved :: MIT License
Classifier: Natural Language :: English
Classifier: Programming Language :: Python :: 3
Classifier: Programming Language :: Python :: 3 :: Only
Classifier: Programming Language :: Python :: 3.6
Classifier: Programming Language :: Python :: 3.7
Classifier: Programming Language :: Python :: 3.8
Classifier: Topic :: Software Development
Classifier: Topic :: Utilities
Requires-Python: >= 3.6
Provides-Extra: all
Provides-Extra: image
Provides-Extra: tests
Provides-Extra: aws
Provides-Extra: datetime
Provides-Extra: io
